[
{
  "model": "auth.group",
  "pk": 1,
  "fields": {
    "name": "Moderator",
    "permissions": [
      29,
      30,
      31,
      32,
      33,
      34,
      35,
      36
    ]
  }
},
{
  "model": "mainapp.customuser",
  "pk": 1,
  "fields": {
    "password": "pbkdf2_sha256$260000$Ttc3WLm9dOxzz04Xv2jnbG$8vjRlLJtCE14+ekjjhN36gxgsQGze6UGogUmcX3arAc=",
    "last_login": "2022-01-07T14:28:32.599Z",
    "is_superuser": true,
    "first_name": "",
    "last_name": "",
    "is_staff": true,
    "is_active": true,
    "date_joined": "2022-01-03T11:55:30.048Z",
    "username": "admin",
    "email": "admin@gmail.com",
    "photo": "",
    "is_seller": true,
    "groups": [],
    "user_permissions": []
  }
},
{
  "model": "mainapp.customuser",
  "pk": 2,
  "fields": {
    "password": "pbkdf2_sha256$260000$eeoLHK40EmdBNtViBibUgy$aPuWFU9WfDA8D78I3p2zNMVkUnXUO2jqzCcfGlj/3JQ=",
    "last_login": "2022-01-07T14:27:57.810Z",
    "is_superuser": false,
    "first_name": "",
    "last_name": "",
    "is_staff": true,
    "is_active": true,
    "date_joined": "2022-01-03T12:02:33.586Z",
    "username": "test1",
    "email": "test1@gmail.com",
    "photo": "",
    "is_seller": true,
    "groups": [
      1
    ],
    "user_permissions": []
  }
},
{
  "model": "mainapp.customuser",
  "pk": 3,
  "fields": {
    "password": "pbkdf2_sha256$260000$JUJwb9eXz9rMWnj2QYIHPY$9mvLS9QtUcmXHXVvYd72iAWzjjk6Ea5x+r//PNWbd/k=",
    "last_login": null,
    "is_superuser": false,
    "first_name": "",
    "last_name": "",
    "is_staff": false,
    "is_active": true,
    "date_joined": "2022-01-03T12:02:58.857Z",
    "username": "test2",
    "email": "test2@gmail.com",
    "photo": "",
    "is_seller": false,
    "groups": [],
    "user_permissions": []
  }
},
{
  "model": "mainapp.category",
  "pk": 1,
  "fields": {
    "name": "R",
    "verbose": "r"
  }
},
{
  "model": "mainapp.category",
  "pk": 2,
  "fields": {
    "name": "Clothes",
    "verbose": "clothes"
  }
},
{
  "model": "mainapp.category",
  "pk": 3,
  "fields": {
    "name": "New category with tons of useful products and magnificent vi",
    "verbose": "new-category-with-tons-of-useful-products-and-magnificent-vi"
  }
},
{
  "model": "mainapp.product",
  "pk": 1,
  "fields": {
    "category": 1,
    "created_by": 1,
    "title": "T",
    "description": "D",
    "image": "",
    "price": "1",
    "in_stock": true,
    "is_active": true,
    "published": "2022-01-03T12:05:51.839Z",
    "updated": "2022-01-03T12:05:51.839Z"
  }
},
{
  "model": "mainapp.product",
  "pk": 2,
  "fields": {
    "category": 1,
    "created_by": 2,
    "title": "New shoes 2",
    "description": "New shoes 2 description",
    "image": "",
    "price": "18.00",
    "in_stock": true,
    "is_active": true,
    "published": "2022-01-03T12:06:18.681Z",
    "updated": "2022-01-03T12:06:18.681Z"
  }
},
{
  "model": "mainapp.product",
  "pk": 3,
  "fields": {
    "category": 3,
    "created_by": 1,
    "title": "Completely new and utterly unbelievable magnificent toaster1",
    "description": "Contrary to popular belief, Lorem Ipsum is not simply random text. It has roots in a piece of classical Latin literature from 45 BC, making it over 2000 years old. Richard McClintock, a Latin professor at Hampden-Sydney College in Virginia, looked up one of the more obscure Latin words, consectetur, from a Lorem Ipsum passage, and going through the cites of the word in classical literature, discovered the undoubtable source. Lorem Ipsum comes from sections 1.10.32 and 1.10.33 of de Finibus Bonorum et Malorum (The Extremes of Good and Evil) by Cicero, written in 45 BC. This book is a treatiseto",
    "image": "",
    "price": "99999.99",
    "in_stock": false,
    "is_active": false,
    "published": "2022-01-03T12:07:00.089Z",
    "updated": "2022-01-03T12:07:00.089Z"
  }
},
{
  "model": "mainapp.product",
  "pk": 5,
  "fields": {
    "category": 3,
    "created_by": 2,
    "title": "Brilliant computer",
    "description": "New computer",
    "image": "",
    "price": "40.44",
    "in_stock": true,
    "is_active": true,
    "published": "2022-01-03T12:08:09.332Z",
    "updated": "2022-01-03T12:08:09.332Z"
  }
},
{
  "model": "mainapp.product",
  "pk": 7,
  "fields": {
    "category": 2,
    "created_by": 1,
    "title": "T-shirt",
    "description": "New T-shirt",
    "image": "",
    "price": "12.65",
    "in_stock": true,
    "is_active": true,
    "published": "2022-01-03T12:09:31.678Z",
    "updated": "2022-01-03T12:09:31.678Z"
  }
},
{
  "model": "mainapp.product",
  "pk": 8,
  "fields": {
    "category": 2,
    "created_by": 2,
    "title": "Gloves",
    "description": "New gloves",
    "image": "",
    "price": "5.54",
    "in_stock": false,
    "is_active": true,
    "published": "2022-01-03T12:09:53.571Z",
    "updated": "2022-01-03T12:09:53.571Z"
  }
},
{
  "model": "account.emailaddress",
  "pk": 1,
  "fields": {
    "user": 1,
    "email": "admin@gmail.com",
    "verified": true,
    "primary": true
  }
},
{
  "model": "account.emailaddress",
  "pk": 2,
  "fields": {
    "user": 2,
    "email": "test1@gmail.com",
    "verified": true,
    "primary": true
  }
},
{
  "model": "account.emailaddress",
  "pk": 3,
  "fields": {
    "user": 3,
    "email": "test2@gmail.com",
    "verified": true,
    "primary": true
  }
}
]